{
  "appPageId" : "7cd60cbf-9c3c-4756-b031-e5d09e77c8ab",
  "componentName" : "siteforce:sldsTwoCol84Layout",
  "dataProviders" : [ ],
  "id" : "a99597cb-5889-4c62-997b-7027e4b92eba",
  "label" : "Article Detail",
  "regions" : [ {
    "id" : "2c92454e-2a3a-4f8e-9ed7-b7f24c8fa6df",
    "regionName" : "header",
    "type" : "region"
  }, {
    "components" : [ {
      "componentAttributes" : {
        "uniqueNameOrId" : "{!urlName}"
      },
      "componentName" : "forceCommunity:breadcrumbs",
      "id" : "10e0025b-7e58-45f7-b3e5-090e5cab0297",
      "renderPriority" : "NEUTRAL",
      "renditionMap" : { },
      "type" : "component"
    }, {
      "componentAttributes" : {
        "enableVoting" : true,
        "recordId" : "{!recordId}",
        "showTitleInArticleHeader" : true,
        "showTopicPills" : true,
        "urlName" : "{!urlName}"
      },
      "componentName" : "selfService:singleArticleView",
      "id" : "a6f059cc-98cb-401c-b9d2-8ea649c7dc16",
      "renderPriority" : "NEUTRAL",
      "renditionMap" : { },
      "type" : "component"
    }, {
      "componentAttributes" : {
        "context" : "RECORD",
        "recordId" : "{!recordId}",
        "width" : "WIDE"
      },
      "componentName" : "forceCommunity:feedPublisher",
      "id" : "ac7b88ea-be29-4bdb-ac13-bd10a3e0760d",
      "renderPriority" : "NEUTRAL",
      "renditionMap" : { },
      "type" : "component"
    }, {
      "componentAttributes" : {
        "canChangeSorting" : false,
        "defaultFilter" : "",
        "defaultSortOrderHomeFeed" : "Relevance",
        "defaultSortOrderTopicsFeed" : "Relevance",
        "feedDesign" : "DEFAULT",
        "hasFeedSearch" : false,
        "subjectId" : "{!recordId}",
        "type" : "Record"
      },
      "componentName" : "forceCommunity:forceCommunityFeed",
      "id" : "7831ce12-6501-4ff7-9639-93f5dd1a9408",
      "renderPriority" : "NEUTRAL",
      "renditionMap" : { },
      "type" : "component"
    } ],
    "id" : "265a677e-7372-430b-9b73-d6590dfc44ee",
    "regionName" : "content",
    "type" : "region"
  }, {
    "components" : [ {
      "componentAttributes" : {
        "buttonAlignment" : "center",
        "buttonBgColor" : "",
        "buttonBgHoverColor" : "",
        "buttonBorderColor" : "",
        "buttonMaxWidth" : 100,
        "buttonRadius" : 0,
        "buttonTextColor" : "",
        "buttonTextHoverColor" : "",
        "recordId" : "{!recordId}",
        "showNotificationMenu" : false
      },
      "componentName" : "forceCommunity:follow",
      "id" : "146e6972-c9f1-4c9b-9090-3af804eaa7aa",
      "renderPriority" : "NEUTRAL",
      "renditionMap" : { },
      "type" : "component"
    }, {
      "componentAttributes" : {
        "numberOfItems" : 5,
        "showViewCounts" : true,
        "title" : "Related Articles"
      },
      "componentName" : "selfService:similarArticles42",
      "id" : "1a7aadf7-bf6c-4dc0-ae3d-7d540c05f860",
      "renderPriority" : "NEUTRAL",
      "renditionMap" : { },
      "type" : "component"
    }, {
      "componentAttributes" : {
        "numberOfArticles" : 5,
        "title" : "Trending Articles",
        "topicId" : "{!topicId}"
      },
      "componentName" : "selfService:topicTrendingArticles42",
      "id" : "9a7b0c19-25c2-480b-a20a-9b315468f7ac",
      "renderPriority" : "NEUTRAL",
      "renditionMap" : { },
      "type" : "component"
    } ],
    "id" : "b13cff6e-25dc-4c81-bfec-c28bd3f3c25a",
    "regionName" : "sidebar",
    "type" : "region"
  }, {
    "components" : [ {
      "componentAttributes" : {
        "askCommunityLabel" : "Ask a Question",
        "buttonBgColor" : "",
        "buttonBgHoverColor" : "",
        "buttonBorderColor" : "",
        "buttonRadius" : 0,
        "buttonTextColor" : "",
        "buttonTextHoverColor" : "",
        "buttonTwoBgColor" : "",
        "buttonTwoBgHoverColor" : "",
        "buttonTwoBorderColor" : "",
        "buttonTwoRadius" : 0,
        "buttonTwoTextColor" : "",
        "buttonTwoTextHoverColor" : "",
        "confirmationMessage" : "Got it!",
        "contactSupportLabel" : "Contact Support",
        "followUpPromptLabel" : "Can we close your question?",
        "headerLabel" : "Don't see what you're looking for?",
        "isAskFollowPromptEnabled" : true,
        "isIncludeArticlesEnabled" : false,
        "isIncludeDiscussionsEnabled" : true,
        "isInitialSatisfactionPromptEnabled" : true,
        "isPublisherDeflectionEnabled" : true,
        "maxSuggestions" : 5,
        "satisfactionPromptLabel" : "Did we help to answer your question?",
        "showDetails" : false,
        "showTopics" : true
      },
      "componentName" : "siteforce:napiliFooter",
      "id" : "10a7772f-de4c-4602-8138-26a550f4d6b0",
      "renderPriority" : "NEUTRAL",
      "renditionMap" : { },
      "type" : "component"
    } ],
    "id" : "8c5f3e44-fbd2-4bfd-9960-7cf0cc69f6d7",
    "regionName" : "footer",
    "type" : "region"
  }, {
    "components" : [ {
      "componentAttributes" : {
        "customHeadTags" : "",
        "description" : "{!Record.Summary}",
        "title" : "{!Record._Title}"
      },
      "componentName" : "forceCommunity:seoAssistant",
      "id" : "c51b0943-d3bd-4932-b5ac-424a2dc9ad88",
      "renditionMap" : { },
      "type" : "component"
    } ],
    "id" : "e79531c3-4e28-4890-aafa-437d6738af41",
    "regionName" : "sfdcHiddenRegion",
    "type" : "region"
  } ],
  "themeLayoutType" : "Inner",
  "type" : "view",
  "viewType" : "article"
}