{
  "appPageId" : "e123c1c3-2e61-4e6d-928e-a4f2c6c47189",
  "componentName" : "community_layout:sldsFlexibleLayout",
  "dataProviders" : [ ],
  "id" : "bd878a89-2a6e-4f92-b724-f321429fecb1",
  "label" : "Check Password",
  "regions" : [ {
    "components" : [ {
      "componentAttributes" : {
        "backgroundImageConfig" : "",
        "backgroundImageOverlay" : "rgba(0,0,0,0)",
        "sectionConfig" : "{\"UUID\":\"d0cc9de2-9d79-4573-8a0f-a08b1072d858\",\"columns\":[{\"UUID\":\"6ed6630e-77f9-4ae4-b61a-5428e5d7ecdd\",\"columnName\":\"Column 1\",\"columnKey\":\"col1\",\"columnWidth\":\"12\",\"seedComponents\":null}]}"
      },
      "componentName" : "community_layout:section",
      "id" : "d0cc9de2-9d79-4573-8a0f-a08b1072d858",
      "regions" : [ {
        "components" : [ {
          "componentAttributes" : { },
          "componentName" : "community_login:communityLogo",
          "id" : "f8f2a36f-79ea-44b7-928f-1f3ed4bd9324",
          "renderPriority" : "NEUTRAL",
          "renditionMap" : { },
          "type" : "component"
        }, {
          "componentAttributes" : {
            "checkEmailMessage" : "Check the email account associated with your username for the link to reset your password. If you didn't get an email, check your Spam folder. Or contact your administrator.",
            "returnButtonLabel" : "Back to login",
            "titleLabel" : "Now check your email"
          },
          "componentName" : "community_login:checkEmail",
          "id" : "47b863e5-cb6e-4d53-bfbf-fcb5f180260d",
          "renderPriority" : "NEUTRAL",
          "renditionMap" : { },
          "type" : "component"
        } ],
        "id" : "6ed6630e-77f9-4ae4-b61a-5428e5d7ecdd",
        "regionLabel" : "Column 1",
        "regionName" : "col1",
        "renditionMap" : { },
        "type" : "region"
      } ],
      "renderPriority" : "NEUTRAL",
      "renditionMap" : { },
      "scopedBrandingSetId" : null,
      "type" : "component"
    } ],
    "id" : "82ac392e-5635-4393-a0aa-552c3077a7f6",
    "regionName" : "content",
    "type" : "region"
  }, {
    "components" : [ {
      "componentAttributes" : {
        "customHeadTags" : "",
        "description" : "",
        "pageTitle" : "Check Password",
        "recordId" : "{!recordId}"
      },
      "componentName" : "community_builder:seoAssistant",
      "id" : "82a3b770-f00c-4edb-8254-32ab9288f57a",
      "renderPriority" : "NEUTRAL",
      "renditionMap" : { },
      "type" : "component"
    } ],
    "id" : "2b7b540b-5ee6-461b-9995-6ad2178d548d",
    "regionName" : "sfdcHiddenRegion",
    "type" : "region"
  } ],
  "themeLayoutType" : "Inner",
  "type" : "view",
  "viewType" : "check-password"
}